{
	"files": [
		{
			"path": "teooria.md",
			"bookmarks": [
				{
					"line": 0,
					"column": 2,
					"label": ""
				},
				{
					"line": 18,
					"column": 2,
					"label": ""
				},
				{
					"line": 54,
					"column": 2,
					"label": ""
				},
				{
					"line": 84,
					"column": 2,
					"label": ""
				},
				{
					"line": 142,
					"column": 2,
					"label": ""
				},
				{
					"line": 200,
					"column": 0,
					"label": ""
				},
				{
					"line": 201,
					"column": 2,
					"label": ""
				},
				{
					"line": 218,
					"column": 2,
					"label": ""
				},
				{
					"line": 259,
					"column": 2,
					"label": ""
				},
				{
					"line": 293,
					"column": 2,
					"label": ""
				},
				{
					"line": 310,
					"column": 2,
					"label": ""
				},
				{
					"line": 358,
					"column": 4,
					"label": ""
				},
				{
					"line": 369,
					"column": 20,
					"label": ""
				},
				{
					"line": 390,
					"column": 9,
					"label": ""
				},
				{
					"line": 418,
					"column": 16,
					"label": ""
				}
			]
		}
	]
}